django_cap-0.3.0.dist-info/METADATA
django_cap-0.3.0.dist-info/WHEEL
django_cap-0.3.0.dist-info/licenses/LICENSE
django_cap.libs/libgcc_s-5b5488a6.so.1
django_cap/__init__.py
django_cap/admin.py
django_cap/apps.py
django_cap/cap_core/README.md
django_cap/cap_core/__init__.py
django_cap/cap_core/_cap_rust.cpython-312-arm-linux-musleabihf.so
django_cap/cap_core/_cap_rust.pyi
django_cap/cap_core/cap.py
django_cap/cap_core/solver.py
django_cap/cap_core/utils.py
django_cap/django_adapter.py
django_cap/django_app_settings.py
django_cap/drf_api/__init__.py
django_cap/example/__init__.py
django_cap/example/urls.py
django_cap/example/views.py
django_cap/example_views.py
django_cap/forms.py
django_cap/migrations/0001_initial.py
django_cap/migrations/__init__.py
django_cap/models.py
django_cap/ninja_api/__init__.py
django_cap/ninja_api/apps.py
django_cap/ninja_api/views.py
django_cap/templates/cap/examples/base.html
django_cap/templates/cap/examples/contact.html
django_cap/templates/cap/examples/index.html
django_cap/templates/cap/examples/success.html
django_cap/templatetags/__init__.py
django_cap/templatetags/django_cap.py
django_cap/urls.py
django_cap/views.py
django_cap-0.3.0.dist-info/RECORD
