Metadata-Version: 2.4
Name: django-cap
Version: 0.3.0
Classifier: Development Status :: 4 - Beta
Classifier: Framework :: Django
Classifier: Framework :: Django :: 5.0
Classifier: Framework :: Django :: 5.1
Classifier: Framework :: Django :: 5.2
Classifier: Intended Audience :: Developers
Classifier: License :: OSI Approved :: Apache Software License
Classifier: Operating System :: OS Independent
Classifier: Programming Language :: Python :: 3
Classifier: Programming Language :: Python :: 3.11
Classifier: Programming Language :: Python :: 3.12
Classifier: Programming Language :: Python :: 3.13
Classifier: Topic :: Internet :: WWW/HTTP :: Dynamic Content
Classifier: Topic :: Security
Classifier: Topic :: Software Development :: Libraries :: Python Modules
Requires-Dist: cryptography>=45.0
Requires-Dist: django>=5.0
Requires-Dist: django-ninja>=1.4 ; extra == 'ninja'
Requires-Dist: djangorestframework>=3.16 ; extra == 'drf'
Requires-Dist: django-unfold>=0.62 ; extra == 'unfold'
Provides-Extra: ninja
Provides-Extra: drf
Provides-Extra: unfold
License-File: LICENSE
Summary: Django implementation of Cap.js Server for Proof of Work captcha
Keywords: django,captcha,proof-of-work,cap,security
Author-email: Somiona <somionat@gmail.com>
License: Apache-2.0
Requires-Python: >=3.11
Project-URL: Homepage, https://github.com/somiona/django_cap
Project-URL: Repository, https://github.com/somiona/django_cap
Project-URL: Bug Tracker, https://github.com/somiona/django-cap/issues
Project-URL: Documentation, https://github.com/somiona/django-cap#readme
